{
  "version": "0.3.24",
  "url": "https://github.com/tomlee680/mh-jido-releases/releases/download/v0.3.24/JidoMH-0.3.24.zip",
  "sha256": "7b5544e32b06ff88e9c78ce3b4e74e3e1b4a2c638ec616955c59f6812c759fda",
  "files_url": "https://github.com/tomlee680/mh-jido-releases/releases/download/v0.3.24/files.json",
  "notes": "- **标定模式(测量,不是修复)**:0.3.23 的客户区改动对无边框窗口是空操作、点击仍偏,且所有日志读数都自洽地显示\"对齐\"——说明错位在代码看不见的那一层(截图帧 vs 屏幕真实显示)。本版重开 `CALIBRATE`:找到师傅后**不自动点**,提示用真鼠标点一次「东海龙王」,被动记录你点的屏幕坐标(零注入),打印 `差值(你-模板)`。差值大=截图与屏幕错位(很可能抓帧选错了多开器窗口层),差值≈0=点击其实在字上、问题是该文字不可点(应改点右上角任务追踪)。量清楚即关闭"
}